biomero_importer/__init__.py
biomero_importer/db_migrate.py
biomero_importer/main.py
biomero_importer/migrations/alembic.ini
biomero_importer/migrations/env.py
biomero_importer/migrations/script.py.mako
biomero_importer/migrations/versions/78d3d6d84aec_add_description_to_imports.py
biomero_importer/utils/__init__.py
biomero_importer/utils/importer.py
biomero_importer/utils/ingest_tracker.py
biomero_importer/utils/initialize.py
biomero_importer/utils/register.py
biomero_importer/utils/upload_order_manager.py
biomero_importer-1.0.0b5.dist-info/licenses/LICENCE
config/sample_groups_list.json
config/sample_upload_order.txt
config/settings.yml
set_up/get_omero_info.py
tests/Barbie1.tif
tests/Barbie2.tif
tests/Barbie3.tif
tests/README.md
tests/requirements.txt
tests/setup_conda_test_env.sh
tests/system_check.py
tests/t_main.py
tests/t_settings.bak
tests/unittests/pyetest.ini
tests/unittests/test_ci_validation.py
tests/unittests/test_edge_cases.py
tests/unittests/test_ingest_tracker.py
tests/unittests/test_integration.py
tests/unittests/test_main.py
tests/unittests/test_upload_order_manager.py
tests/unittests/test_config/sample_groups_list.json
tests/unittests/test_config/sample_upload_order.txt
tests/unittests/test_config/settings.yml
tests/unittests/test_config/test.log
biomero_importer-1.0.0b5.dist-info/METADATA
biomero_importer-1.0.0b5.dist-info/WHEEL
biomero_importer-1.0.0b5.dist-info/top_level.txt
biomero_importer-1.0.0b5.dist-info/RECORD
