Metadata-Version: 2.4
Name: biomero-importer
Version: 1.0.0b5
Summary: BIOMERO.importer - Automated Data Import System (formerly OMERO ADI)
Author-email: Rodrigo Rosas-Bertolini <cellularimaging@amsterdamumc.nl>
Project-URL: Homepage, https://github.com/Cellular-Imaging-Amsterdam-UMC/BIOMERO.importer
Project-URL: Documentation, https://cellular-imaging-amsterdam-umc.github.io/NL-BIOMERO/
Project-URL: Repository, https://github.com/Cellular-Imaging-Amsterdam-UMC/BIOMERO.importer
Classifier: Programming Language :: Python :: 3
Classifier: Programming Language :: Python :: 3.12
Classifier: Programming Language :: Python :: 3.13
Classifier: Programming Language :: Python :: 3.14
Classifier: License :: OSI Approved :: Apache Software License
Classifier: Operating System :: OS Independent
Requires-Python: >=3.12
License-File: LICENCE
Requires-Dist: ezomero==3.2.1
Requires-Dist: pandas>=2.2.1
Requires-Dist: numpy>=1.26.4
Requires-Dist: openpyxl>=3.1.2
Requires-Dist: python-dotenv>=1.0.1
Requires-Dist: pytest>=8.2.1
Requires-Dist: sqlalchemy>=2.0.28
Requires-Dist: psycopg2>=2.9.7
Requires-Dist: zarr>=3
Requires-Dist: alembic>=1.13
Provides-Extra: test
Requires-Dist: pytest-cov; extra == "test"
Requires-Dist: mock; extra == "test"
Requires-Dist: psycopg2-binary; extra == "test"
Dynamic: license-file
